ards_sll_scrape.py
ards_sll_scrape-0.2.4.dist-info/METADATA
ards_sll_scrape-0.2.4.dist-info/WHEEL
ards_sll_scrape-0.2.4.dist-info/top_level.txt
ards_sll_scrape-0.2.4.dist-info/RECORD
